tartex/__about__.py
tartex/__init__.py
tartex/_completion.py
tartex/_git_rev.py
tartex/_latex.py
tartex/_parse_args.py
tartex/_tar.py
tartex/tartex.py
tartex/data/tartex-completion.bash
tartex/data/tartex-completion.fish
tartex/data/tartex-completion.zsh
tartex/utils/hash_utils.py
tartex/utils/msg_utils.py
tartex/utils/tar_utils.py
tartex/utils/tex_utils.py
tartex/utils/xdgdir_utils.py
tartex/man/tartex.1
tartex-0.11.1.dist-info/METADATA
tartex-0.11.1.dist-info/WHEEL
tartex-0.11.1.dist-info/entry_points.txt
tartex-0.11.1.dist-info/licenses/LICENSE.txt
tartex-0.11.1.dist-info/RECORD
