Metadata-Version: 2.4
Name: tartex
Version: 0.11.1
Summary: Tar all files needed to re-compile your LaTeX project
Project-URL: Documentation, https://github.com/badshah400/tartex#readme
Project-URL: Issues, https://github.com/badshah400/tartex/issues
Project-URL: Source, https://github.com/badshah400/tartex
Author-email: Atri Bhattacharya <atrib@duck.com>
License-Expression: MIT
License-File: LICENSE.txt
Keywords: LaTeX,latexmk,tar
Classifier: Development Status :: 4 - Beta
Classifier: License :: OSI Approved :: MIT License
Classifier: Operating System :: OS Independent
Classifier: Programming Language :: Python
Classifier: Programming Language :: Python :: 3.9
Classifier: Programming Language :: Python :: 3.10
Classifier: Programming Language :: Python :: 3.11
Classifier: Programming Language :: Python :: 3.12
Classifier: Programming Language :: Python :: 3.13
Classifier: Programming Language :: Python :: Implementation :: CPython
Classifier: Programming Language :: Python :: Implementation :: PyPy
Requires-Python: >=3.9
Requires-Dist: rich
